{
  "name": "Daisy Morrison",
  "age": 19,
  "address": {
    "street": "Defer Way",
    "city": "Tepmivuk",
    "state": "NC",
    "zip": "71005"
  },
  "contact": {
    "phone": "(423) 813-8482",
    "servicePhone": "800854194"
  },
  "birthday": "1987-01-28T02:03:12.907Z",
  "ip": "146.148.23.112",
  "foo": "bar",
  "profile": {
    "about": "Upwi we bumu ton zeho sig seg mi elemih va bedvu ala. Cusi ezafegot ditib ifehov sirba agubusen mofzu zamlo diga midni zip uve nifopar bu bobow eja uva ecajopo. Efevase patow aw keg bifaifo no fi ibakevju vurevuk celegnuw fokdit tofalru kuvvega herkes jejak uwadaijo.",
    "bio": "Ligu zi feposudo hif dozmu mudgop ubu ico lekjobsu huaj ew cedcoh osesinam be puczoc nan. Wa hupuw od wimek jina kehip dioruzog vop peda tuv zidopoho bewpevu muzi vok wagedlu. Jucuviru bod vi vijades uritaw ane gukok nab midaw nemmu aholaef bocusam kabup ral egumatido are vucdom. Kobaw ge netukhoz si de ovo zodris sowwu hifocwe ad vulibcic wehla haumo gir dizfir. Odiodimub vemu kapen sobe fu ga ziwibu wic imikalzoh ro dofbu be dev zepuv bir mupnihja. Figca dedpiknuf meho zipgozi onuubu pabdosba vuc aloce guvbo emese zi huta wo wi dobubi kejow kolwaak cajvozopi. Fik ze ohmib vu oco robiz zuc bib ceeki dite zowuh zaiteipi vus ig pimunuwo sok."
  },
  "apiKey": "20c76fb0769220847bb369d57ffcf7f5541cff29e2216d7b69289075fe18b289",
  "currency": {
    "code": "ZAR",
    "name": "South Africa Rand"
  }
}